poetries/__init__.py
poetries/base.py
poetries/error.py
poetries/node.py
poetries/trie.py
poetries-1.0.0.dist-info/METADATA
poetries-1.0.0.dist-info/WHEEL
poetries-1.0.0.dist-info/top_level.txt
poetries-1.0.0.dist-info/RECORD
