Metadata-Version: 2.1
Name: poetries
Version: 1.0.0
Summary: A thread safe implementation of a Trie.
Home-page: https://github.com/soumasish/poetries
Author: Soumasish Goswami
Author-email: hello@soumasish.io
License: MIT
Platform: UNKNOWN
Classifier: License :: OSI Approved :: MIT License
Classifier: Programming Language :: Python :: 3
Classifier: Programming Language :: Python :: 3.7
Requires-Dist: readerwriterlock
